{
  "placeholderImages": [
    {
      "id": "hero-cake-new",
      "description": "A delicious pink strawberry cake on a stand with fresh berries",
      "imageUrl": "https://images.unsplash.com/photo-1542007920-992d2c424d09?crop=entropy&cs=tinysrgb&fit=max&fm=jpg&ixid=M3w3NDE5ODJ8MHwxfHNlYXJjaHwxNnx8Y2FrZXxlbnwwfHx8fDE3NjY3MjkzMDF8MA&ixlib=rb-4.1.0&q=80&w=1080",
      "imageHint": "pink cake"
    },
    {
      "id": "birthday-cake-new",
      "description": "Colorful birthday cake with sprinkles and candles",
      "imageUrl": "https://images.unsplash.com/photo-1693059740560-21151639561f?crop=entropy&cs=tinysrgb&fit=max&fm=jpg&ixid=M3w3NDE5ODJ8MHwxfHNlYXJjaHwzfHxCaXJ0aGRheSUyMENha2VzfGVufDB8fHx8MTc2NjczMzUyNHww&ixlib=rb-4.1.0&q=80&w=1080",
      "imageHint": "birthday cake"
    },
    {
      "id": "bento-cake-new",
      "description": "Cute small bento cake in a lunchbox with korean style decoration",
      "imageUrl": "https://images.unsplash.com/photo-1605807646983-377bc5a76493?crop=entropy&cs=tinysrgb&fit=max&fm=jpg&ixid=M3w3NDE5ODJ8MHwxfHNlYXJjaHw5fHxiZW50byUyMGNha2V8ZW58MHx8fHwxNzY2NzM0MTAzfDA&ixlib=rb-4.1.0&q=80&w=1080",
      "imageHint": "bento cake"
    },
    {
      "id": "wedding-cake-new",
      "description": "Elegant white tiered wedding cake with floral decorations",
      "imageUrl": "https://images.unsplash.com/photo-1519654793190-2e8a4806f1f2?crop=entropy&cs=tinysrgb&fit=max&fm=jpg&ixid=M3w3NDE5ODJ8MHwxfHNlYXJjaHwzfHxXZWRkaW5nJTIwQ2FrZXN8ZW58MHx8fHwxNzY2NzMzNTQzfDA&ixlib=rb-4.1.0&q=80&w=1080",
      "imageHint": "wedding cake"
    },
    {
      "id": "custom-cake-new",
      "description": "Unique custom shaped cake with creative design",
      "imageUrl": "https://images.unsplash.com/photo-1693059857299-3f5ee0eaad7e?crop=entropy&cs=tinysrgb&fit=max&fm=jpg&ixid=M3w3NDE5ODJ8MHwxfHNlYXJjaHwyfHxjdXN0b20lMjBjYWtlfGVufDB8fHx8MTc2NjczMzYzN3ww&ixlib=rb-4.1.0&q=80&w=1080",
      "imageHint": "creative cake"
    },
    {
      "id": "avatar-female",
      "description": "Avatar for a female user",
      "imageUrl": "https://images.unsplash.com/photo-1586297135537-94bc9ba060aa?ixlib=rb-4.0.3&ixid=M3wxMjA3fDB8MHxwaG90by1wYWdlfHx8fGVufDB8fHx8fA%3D%3D&auto=format&fit=crop&w=1480&q=80",
      "imageHint": "woman avatar"
    },
    {
      "id": "midnight-chocolate-dream",
      "description": "Dark chocolate cake with ganache drip",
      "imageUrl": "https://images.unsplash.com/photo-1578985545062-69928b1d9587?ixlib=rb-4.0.3&ixid=M3wxMjA3fDB8MHxwaG90by1wYWdlfHx8fGVufDB8fHx8fA%3D%3D&auto=format&fit=crop&w=1335&q=80",
      "imageHint": "dark chocolate cake"
    },
    {
      "id": "classic-ribbon-cake",
      "description": "Colorful layered ribbon cake slice",
      "imageUrl": "https://images.unsplash.com/photo-1621532533363-bce26f8c7075?ixlib=rb-4.0.3&ixid=M3wxMjA3fDB8MHxwaG90by1wYWdlfHx8fGVufDB8fHx8fA%3D%3D&auto=format&fit=crop&w=1287&q=80",
      "imageHint": "colorful layered cake"
    },
    {
      "id": "berry-bliss-gateau",
      "description": "Strawberry gateau cake with fresh berries",
      "imageUrl": "https://images.unsplash.com/photo-1611293388250-580290aa3374?ixlib=rb-4.0.3&ixid=M3wxMjA3fDB8MHxwaG90by1wYWdlfHx8fGVufDB8fHx8fA%3D%3D&auto=format&fit=crop&w=1287&q=80",
      "imageHint": "strawberry gateau"
    },
    {
      "id": "red-velvet-cupcakes",
      "description": "Red velvet cupcakes with cream cheese frosting",
      "imageUrl": "https://images.unsplash.com/photo-1614707267537-7892336bf09a?ixlib=rb-4.0.3&ixid=M3wxMjA3fDB8MHxwaG90by1wYWdlfHx8fGVufDB8fHx8fA%3D%3D&auto=format&fit=crop&w=1287&q=80",
      "imageHint": "red velvet cupcakes"
    },
    {
      "id": "golden-butter-cake",
      "description": "Simple golden butter cake slice",
      "imageUrl": "https://images.unsplash.com/photo-1586612548834-145a54335356?ixlib=rb-4.0.3&ixid=M3wxMjA3fDB8MHxwaG90by1wYWdlfHx8fGVufDB8fHx8fA%3D%3D&auto=format&fit=crop&w=1287&q=80",
      "imageHint": "butter cake slice"
    },
    {
      "id": "custom-wedding-tier",
      "description": "Elegant wedding tier cake",
      "imageUrl": "https://images.unsplash.com/photo-1511382434135-d5963a56461f?ixlib=rb-4.0.3&ixid=M3wxMjA3fDB8MHxwaG90by1wYWdlfHx8fGVufDB8fHx8fA%3D%3D&auto=format&fit=crop&w=1287&q=80",
      "imageHint": "elegant wedding cake"
    },
    {
      "id": "coffee-walnut-delight",
      "description": "Coffee walnut cake with nuts on top",
      "imageUrl": "https://images.unsplash.com/photo-1551024601-bec78aea704b?ixlib=rb-4.0.3&ixid=M3wxMjA3fDB8MHxwaG90by1wYWdlfHx8fGVufDB8fHx8fA%3D%3D&auto=format&fit=crop&w=1364&q=80",
      "imageHint": "coffee walnut cake"
    },
    {
      "id": "zesty-lemon-drizzle",
      "description": "Lemon cake with yellow drizzle",
      "imageUrl": "https://images.unsplash.com/photo-1547414368-ac947d00491d?ixlib=rb-4.0.3&ixid=M3wxMjA3fDB8MHxwaG90by1wYWdlfHx8fGVufDB8fHx8fA%3D%3D&auto=format&fit=crop&w=1287&q=80",
      "imageHint": "lemon drizzle cake"
    },
    {
      "id": "about-us-image",
      "description": "A female baker smiling in her kitchen with a freshly baked cake",
      "imageUrl": "https://images.unsplash.com/photo-1625489409904-324a5e9591e1?crop=entropy&cs=tinysrgb&fit=max&fm=jpg&ixid=M3w3NDE5ODJ8MHwxfHNlYXJjaHwyfHxmZW1hbGUlMjBiYWtlcnxlbnwwfHx8fDE3NjY3MzA0NzF8MA&ixlib=rb-4.1.0&q=80&w=1080",
      "imageHint": "baker kitchen"
    }
  ]
}